Workbook
Name \p: #N/A
Name ___6: #REF!
Name ___8: #REF!
Name ___BTM150: #REF!
Name ___BTM200: #REF!
Name ___BTM50: #REF!
Name ___C: #REF!
Name ___CON1: #REF!
Name ___CON2: #REF!
Name ___EXC1: #REF!
Name ___EXC2: #REF!
Name ___hom2: #REF!
Name ___msl100: #REF!
Name ___msl200: #REF!
Name ___msl250: #REF!
Name ___msl300: #REF!
Name ___msl400: #REF!
Name ___msl800: #REF!
Name ___mui100: #REF!
Name ___mui105: #REF!
Name ___mui108: #REF!
Name ___mui130: #REF!
Name ___mui140: #REF!
Name ___mui160: #REF!
Name ___mui180: #REF!
Name ___mui250: #REF!
Name ___mui271: #REF!
Name ___mui320: #REF!
Name ___mui45: #REF!
Name ___mui50: #REF!
Name ___mui54: #REF!
Name ___mui65: #REF!
Name ___mui75: #REF!
Name ___mui80: #REF!
Name ___NET2: #REF!
Name ___R: #REF!
Name ___sat10: #REF!
Name ___sat12: #REF!
Name ___sat14: #REF!
Name ___sat16: #REF!
Name ___sat20: #REF!
Name ___sat8: #REF!
Name ___sua20: #REF!
Name ___sua30: #REF!
Name ___vbt150: #REF!
Name ___vbt200: #REF!
Name ___vbt210: #REF!
Name ___vbt300: #REF!
Name ___vbt400: #REF!
Name ___vxm100: #REF!
Name ___vxm300: #REF!
Name ___vxm500: #REF!
Name ___vxm75: #REF!
Name __6: #REF!
Name __8: #REF!
Name __BTM150: #REF!
Name __BTM200: #REF!
Name __BTM50: #REF!
Name __C: #REF!
Name __CON1: #REF!

Sheet Cover
C1: CONSOLIDATED FINANCIAL STATEMENTS FOR PAST FIVE QUARTERS - BHARTI AIRTEL LIMITED
C2: [AS PER INDIAN ACCOUNTING STANDARDS (Ind-AS)]
C6: Schedule | E6: INDEX
C8: Financial Indicators
C10: 1 | E10: Consolidated Statements of Operations as per Indian Accounting Standards (Ind-AS)
C12: 2 | E12: Consolidated Balance Sheet as per Indian Accounting Standards (Ind-AS)
C14: 3 | E14: Consolidated Statement of Cash Flows as per Indian Accounting Standards (Ind-AS)
C16: 4 | E16: Consolidated Summarised Statement of Operations (net of inter segment eliminations)
C18: 5 | E18: Schedules to Financial Statements
C21: Operational Indicators
C23: 6 | E23: Operational Performance

Sheet Trends file-1
A1: INDEX | B1: CONSOLIDATED FINANCIAL STATEMENTS - BHARTI AIRTEL LIMITED
A3: 1 | B3: Consolidated Statement of Operations as per Indian Accounting Standards (Ind-AS)
A5: =A3+0.1 -> 1.1 | B5: Consolidated Summarized Statement of Income Net of Inter Segment Eliminations
G6: Amount in Rs Mn, except ratios
B7: Particulars | C7: Quarter Ended
C8: 44651 | D8: 44561 | E8: 44469 | F8: 44377 | G8: 44286
B10: Income
B11: Revenue | C11: 315003 | D11: 298666 | E11: 283264 | F11: 268536 | G11: 257473
B12: Other income | C12: 186 | D12: 1971 | E12: 1088 | F12: 2098 | G12: 839.3
B13: Finance Income
B14: Total | C14: 315189 | D14: 300637 | E14: 284352 | F14: 270634 | G14: 258312.3
B16: Expenses
B17: Network operating expenses | C17: 65458 | D17: 64986 | E17: 61788 | F17: 57973 | G17: 59179
B18: Access Charges | C18: 17505 | D18: 17232 | E18: 16708 | F18: 16166 | G18: 15649
B19: License fee / spectrum charges (revenue share) | C19: 30089 | D19: 27298 | E19: 26794 | F19: 26455 | G19: 25011.905
C20: 0 | D20: 0 | E20: 0 | F20: 0 | G20: 0
B21: Employee benefits | C21: 11642 | D21: 11336 | E21: 11010 | F21: 10345 | G21: 9989
B22: Sales and marketing expenses | C22: 15327 | D22: 14425 | E22: 12670 | F22: 10613 | G22: 11484
B23: Other expenses | C23: 14579 | D23: 16361 | E23: 16189 | F23: 17181 | G23: 12840.658
B25: Total | C25: 154600 | D25: 151638 | E25: 145159 | F25: 138733 | G25: 134153.56
B28: Profit from operating activites before depreciation, amortization and exceptional items | C28: 160589 | D28: 148999 | E28: 139193 | F28: 131901 | G28: 124157.74
B31: Depreciation and amortisation | C31: 85826 | D31: 85472 | E31: 82472 | F31: 77137 | G31: 75019.15
B32: Finance costs | C32: 40593 | D32: 43671 | E32: 39641 | F32: 42257 | G32: 38606
B33: Finance income | C33: 0 | D33: 0 | E33: 0 | F33: 0 | G33: 0
B34: Finance Income | C34: 0 | D34: 0 | E34: 0 | F34: 0 | G34: 0
B35: Non-operating income / expenses, (net) | C35: 0 | D35: 0 | E35: 0 | F35: 0 | G35: 0
B36: Share of results of joint ventures and associates | C36: -7136 | D36: -6161 | E36: -5988 | F36: -4947 | G36: -5274
B37: Other Expenses
B39: Profit before exceptional items and tax | C39: 41306 | D39: 26017 | E39: 23068 | F39: 17454 | G39: 15806.587
B42: Exceptional items | C42: -9062 | D42: -398 | E42: -7221 | F42: -305 | G42: -4404
B45: Profit before tax | C45: 50368 | D45: 26415 | E45: 30289 | F45: 17759 | G45: 20210.587
B48: Tax expense
B49: Current tax | C49: 7765 | D49: 7922 | E49: 7370 | F49: 7274 | G49: 6458
B50: Deferred tax | C50: 5453 | D50: 1986 | E50: 2938 | F50: 1071 | G50: -1357
B53: Profit for the period | C53: 37150 | D53: 16507 | E53: 19981 | F53: 9414 | G53: 15109.587
B56: Profit / (loss) from discontinued operation before tax | C56: 0 | D56: 0 | E56: 0 | F56: 0 | G56: 0
B57: Tax expense / (credit) of discontinued operation | C57: 0 | D57: 0 | E57: 0 | F57: 0 | G57: 0
B58: Profit for the period from discontinued operations | C58: 0 | D58: 0 | E58: 0 | F58: 0 | G58: 0
B60: Profit / (Loss) for the period | C60: 37150 | D60: 16507 | E60: 19981 | F60: 9414 | G60: 15109.587
B64: Consolidated Statement of Comprehensive Income
G66: Amount in Rs Mn, except ratios
B67: Particulars | C67: Quarter Ended
C68: =C8 -> 44651 | D68: =D8 -> 44561 | E68: =E8 -> 44469 | F68: =F8 -> 44377 | G68: =G8 -> 44286
B69: Profit for the period | C69: 37150 | D69: 16507 | E69: 19981 | F69: 9414 | G69: 15109.587
B70: Other comprehensive income ('OCI'):
B71: Items to be reclassified subsequently to profit or loss :
B72: Net gains / (losses) due to foreign currency translation differences | C72: 1631.7785 | D72: 356.02744 | E72: 1079.0562 | F72: 4620.3881 | G72: -5873.7518
B73: Gains / (losses) on net investments hedge | C73: -4042.7785 | D73: -837.02744 | E73: 1014.9438 | F73: -2536.3881 | G73: -610.24817
B74: Gains / (Losses) on cash flow hedge | C74: 0 | D74: 0 | E74: 0 | F74: 0 | G74: 0
B75: Gains / (losses) on fair value through OCI investments | C75: 0 | D75: 0 | E75: 0 | F75: 0 | G75: 0
B76: Tax credit / (charge) | C76: 1035 | D76: 157 | E76: -471 | F76: 548 | G76: 340
C77: -1376 | D77: -324 | E77: 1623 | F77: 2632 | G77: -6144
B79: Items not to be reclassified to profit or loss :
B80: Re-measurement gains / (losses) on defined benefit plans | C80: 50.339569 | D80: 78.676229 | E80: -47.141923 | F80: -125.79792 | G80: 41.667661
B81: Share of joint ventures and associates | C81: 16.200009 | D81: 15.986561 | E81: 1.939817 | F81: 1.217351 | G81: 10.471602
B82: Tax credit / (charge) | C82: -9 | D82: -3.414924 | E82: 8.889647 | F82: 13.525277 | G82: -13.650591
C83: 57.539578 | D83: 92 | E83: -36.312459 | F83: -111.05529 | G83: 38.488672
B85: Other comprehensive income / (loss) for the period | C85: -1318.5604 | D85: -232 | E85: 1586.6875 | F85: 2520.9447 | G85: -6105.5113
B87: Total comprehensive income / (loss) for the period | C87: 35831.34 | D87: 16275 | E87: 21567.688 | F87: 11934.945 | G87: 9004.0758
B89: Profit for the period Attributable to: | C89: 37150 | D89: 16507 | E89: 19981 | F89: 9414 | G89: 15109.85
B90: Owners of the Parent | C90: 20078 | D90: 8296 | E90: 11340 | F90: 2835 | G90: 7591.8501
B91: Non-controlling interests | C91: 17072 | D91: 8211 | E91: 8641 | F91: 6579 | G91: 7518
B94: Other comprehensive income / (loss) for the period attributable to : | C94: -1318.5604 | D94: -232 | E94: 1586.6875 | F94: 2520.9447 | G94: -6105.5113
B95: Owners of the Parent | C95: -4482 | D95: -706 | E95: 964 | F95: -302 | G95: -3435.8501
B96: Non-controlling interests | C96: 3163 | D96: 474 | E96: 622 | F96: 2823 | G96: -2670
B99: Total comprehensive income / (loss) for the period attributable to : | C99: 35831.34 | D99: 16275 | E99: 21567.688 | F99: 11934.945 | G99: 9004.0758
B100: Owners of the Parent | C100: 15596 | D100: 7590 | E100: 12304 | F100: 2533 | G100: 4156
B101: Non-controlling interests | C101: 20235 | D101: 8685 | E101: 9263 | F101: 9402 | G101: 4848
B104: Earnings per share (Face value : Rs. 5/- each) (In Rupees) from Continuing and Discontinuing Operations
B105: Basic | C105: 3.5902816 | D105: 1.4913116 | E105: 2.0559738 | F105: 0.51400657 | G105: 1.3784284
B106: Diluted | C106: 3.5488333 | D106: 1.4770924 | E106: 2.0559738 | F106: 0.51400657 | G106: 1.3784284

Sheet Trends file-2 
A1: INDEX | B1: CONSOLIDATED FINANCIAL STATEMENTS - BHARTI AIRTEL LIMITED
A3: 2 | B3: Consolidated Summarized Balance Sheet (As per Ind AS)
G6: Amount in Rs Mn
B7: Particulars | C7: As at | D7: As at | E7: As at | F7: As at | G7: As at
C8: ='Trends file-1'!C8 -> 44651 | D8: ='Trends file-1'!D8 -> 44561 | E8: ='Trends file-1'!E8 -> 44469 | F8: ='Trends file-1'!F8 -> 44377 | G8: ='Trends file-1'!G8 -> 44286
B9: Assets
B11: Non-current assets
B12: Property, plant and equipment (Incl CWIP) | C12: 1270397 | D12: 1259219 | E12: 1246145 | F12: 1213714 | G12: 1189828
B15: Intangible assets | C15: 1229983 | D15: 1242858 | E15: 1261001 | F15: 1261199 | G15: 1102233
B16: Right-of-use assets | C16: 0 | D16: 0 | E16: 0 | F16: 0 | G16: 0
B17: Investment in joint ventures and associates | C17: 284268 | D17: 252558 | E17: 245656 | F17: 239222 | G17: 234346
B18: Financial Assets
B19: - Investments | C19: 609 | D19: 471 | E19: 469 | F19: 471 | G19: 377
B23: - Others | C23: 22733 | D23: 22846 | E23: 23405 | F23: 23422 | G23: 23402
B25: Income & Deferred tax assets (net) | C25: 216729 | D25: 222564 | E25: 221408 | F25: 222493 | G25: 222103
B26: Other non-current assets | C26: 91562 | D26: 84316 | E26: 79533 | F26: 82147 | G26: 140460
C27: 3116281 | D27: 3084832 | E27: 3077617 | F27: 3042668 | G27: 2912749
B29: Current assets
B31: Financial Assets
B32: - Investments | C32: 8614 | D32: 4440 | E32: 70632 | F32: 1970 | G32: 40781
B34: - Trade receivables | C34: 40562 | D34: 49846 | E34: 50350 | F34: 47707 | G34: 36377
B35: - Cash and bank balance | C35: 60959 | D35: 73015 | E35: 61707 | F35: 84917 | G35: 80859
B36: - Bank deposits | C36: 73984 | D36: 68564 | E36: 58075 | F36: 42444 | G36: 53802
B38: - Receivable from sale of tower assets | C38: 0 | D38: 0 | E38: 0 | F38: 0 | G38: 0
B39: - Others | C39: 215258 | D39: 208794 | E39: 201740 | F39: 198115 | G39: 192448
B40: Current tax assets | C40: 0 | D40: 0 | E40: 0 | F40: 0 | G40: 0
B41: Other current assets | C41: 120902 | D41: 132449 | E41: 138239 | F41: 140772 | G41: 143262
C46: 520279 | D46: 537108 | E46: 580743 | F46: 515925 | G46: 547529
B49: Total Assets | C49: 3636560 | D49: 3621940 | E49: 3658360 | F49: 3558593 | G49: 3460278
B55: Equity and liabilities
B56: Equity
B60: Equity attributable to owners of the Parent | C60: 665543 | D60: 658630 | E60: 601874 | F60: 592034 | G60: 589527
B61: Non-controlling interests ('NCI') | C61: 253807 | D61: 229006 | E61: 233642 | F61: 228909 | G61: 222739
C62: 919350 | D62: 887636 | E62: 835516 | F62: 820943 | G62: 812266
B64: Non-current liabilities
B65: Financial Liabilities
B66: - Borrowings | C66: 1425912 | D66: 1449385 | E66: 1562933 | F66: 1493080 | G66: 1356689
B68: - Others | C68: 90290 | D68: 141397 | E68: 132013 | F68: 93167 | G68: 122393
B70: Lease liabilities | C70: 0 | D70: 0 | E70: 0 | F70: 0 | G70: 0
B71: Deferred tax liabilities (net) | C71: 24488 | D71: 20906 | E71: 19068 | F71: 16709 | G71: 16107
B72: Other non-current liabilities | C72: 36260 | D72: 36675 | E72: 36792 | F72: 37351 | G72: 36464
C73: 1576950 | D73: 1648363 | E73: 1750806 | F73: 1640307 | G73: 1531653
B75: Current liabilities
B76: Financial Liabilities
B77: - Borrowings | C77: 270867 | D77: 235054 | E77: 240899 | F77: 195249 | G77: 271163
B80: - Trade Payables | C80: 292741 | D80: 308141 | E80: 298625 | F80: 304919 | G80: 278721
B81: - Others | C81: 195409.7 | D81: 161477.07 | E81: 167600.25 | F81: 242530.46 | G81: 202187.03
B83: Lease liabilities | C83: 0 | D83: 0 | E83: 0 | F83: 0 | G83: 0
B84: Current tax liabilities (net) | C84: 20725 | D84: 16970 | E84: 14603 | F84: 10547 | G84: 15199
B85: Other current liabilities | C85: 360517 | D85: 364299 | E85: 350311 | F85: 344098 | G85: 349089
B86: Liabilities-held-for-sale
C89: 1140259.7 | D89: 1085941.1 | E89: 1072038.3 | F89: 1097343.5 | G89: 1116359
B92: Total liabilities | C92: 2717209.7 | D92: 2734304.1 | E92: 2822844.3 | F92: 2737650.5 | G92: 2648012
B93: Total equity and liabilities | C93: 3636559.7 | D93: 3621940.1 | E93: 3658360.3 | F93: 3558593.5 | G93: 3460278
C99: =C93-C49 -> -0.297748 | D99: =D93-D49 -> 0.071595 | E99: =E93-E49 -> 0.250429 | F99: =F93-F49 -> 0.459642 | G99: =G93-G49 -> 0.033267

Sheet Trends file-3
A1: INDEX | B1: CONSOLIDATED FINANCIAL STATEMENTS - BHARTI AIRTEL LIMITED
A3: 3 | B3: Consolidated Statement of Cash Flows
G6: ='Trends file-2 '!$G$6 -> Amount in Rs Mn
B7: Particulars | C7: Quarter Ended
C8: ='Trends file-1'!C8 -> 44651 | D8: ='Trends file-1'!D8 -> 44561 | E8: ='Trends file-1'!E8 -> 44469 | F8: ='Trends file-1'!F8 -> 44377 | G8: ='Trends file-1'!G8 -> 44286
B9: Cash flows from operating activities
B11: Profit before tax | C11: 50366.798 | D11: 26415.599 | E11: 30288.837 | F11: 17758.731 | G11: 20210.836
B13: Adjustments for -
B14: Depreciation and amortisation | C14: 85825.115 | D14: 85471.92 | E14: 82472.61 | F14: 77136.879 | G14: 75022.563
B15: Finance costs | C15: 40529.289 | D15: 43280.109 | E15: 39384.503 | F15: 42046.813 | G15: 39090.489
B17: Net gain on FVTPL investments | C17: -164.19316 | D17: -520.92414 | E17: -139.65321 | F17: -242.43073 | G17: -207.57086
B18: Interest income | C18: -1026.4862 | D18: -424.32819 | E18: -413.08697 | F18: -343.06079 | G18: -337.84937
B19: Net loss/ (gain) on derivative financial instruments | C19: -423.70255 | D19: 865.89874 | E19: 1357.5506 | F19: -853.11663 | G19: 524.50847
B20: Net fair value gain on financial instruments | C20: 0 | D20: 0 | E20: 0 | F20: 0 | G20: 0
B21: (Gain) / loss on deemed disposal of subsidiary | C21: 0 | D21: 0 | E21: 0 | F21: 0 | G21: 0
B22: Other non-cash items | C22: -10473.727 | D22: -6584.3974 | E22: -12792.489 | F22: -2411.339 | G22: -10394.379
B24: Operating cash flow before changes in working capital | C24: 164633 | D24: 148505 | E24: 140160 | F24: 133093 | G24: 123908
B25: Changes in working capital -
B26: Trade receivables | C26: 8373.1804 | D26: 257.71678 | E26: -2534.0897 | F26: -13227.643 | G26: 10361.824
B27: Trade payables | C27: -22111.701 | D27: 5265.4804 | E27: -13296.817 | F27: 25267.04 | G27: -15779.757
B31: Other assets and liabilities | C31: -8338.3573 | D31: 10000.397 | E31: 6259.469 | F31: -10386.23 | G31: 4858.349
B33: Net cash generated from operations before tax and dividend | C33: 142556 | D33: 164028 | E33: 130588 | F33: 134746 | G33: 123348
B36: Income tax paid | C36: 1298.4733 | D36: -6570.5442 | E36: -3954.7487 | F36: -12525.528 | G36: -3379.9177
B38: Net cash generated from operating activities (a) | C38: 143854 | D38: 157457 | E38: 126633 | F38: 122220 | G38: 119968
B40: Cash flows from investing activities
B42: Net (Purchase) / proceeds from sale of PPE | C42: -50475.615 | D42: -67699.524 | E42: -60888.324 | F42: -71552.376 | G42: -69260.995
B43: Purchase of intangible assets, spectrum- DPL | C43: -38999.46 | D43: -132229.61 | E43: -8080.6512 | F43: -3765.2497 | G43: -78484.754
B44: Net movement in current investments | C44: -10681.491 | D44: 60065.181 | E44: -83058.411 | F44: 54972.163 | G44: -53467.022
B45: Proceeds from Sale of Spectrum | C45: 0 | D45: 0 | E45: 10048 | F45: 0 | G45: 0
B46: Net (Purchase) / Sale of non-current investments | C46: -13.877826 | D46: -0.43191884 | E46: 0.06127117 | F46: -75.061884 | G46: -16.541167
B49: Cash acquired on business combination
B50: Sale of tower assets | C50: 2566.6618 | D50: 3319.6666 | E50: 0 | F50: 0 | G50: 0
B51: Investment in joint venture / associate | C51: -25289 | D51: -919 | E51: 0 | F51: 0 | G51: -51.487661
B52: Loan given to subsidiaries | C52: 0 | D52: 0 | E52: 8 | F52: 0 | G52: 0
B53: Adjustment on account of deemed disposal of subsidiary | C53: 0 | D53: 0 | E53: 0 | F53: 0 | G53: 0
B54: Dividend received | C54: 0 | D54: 0 | E54: 0 | F54: 0 | G54: 20039
B55: Interest received | C55: 2678.3359 | D55: 581.4318 | E55: 401.06621 | F55: 392.03663 | G55: 374.52813
B56: Repayment of Loan given to Joint Venture/Associate | C56: 0 | D56: 0 | E56: 0 | F56: 0 | G56: 0
B58: Net cash (used in) / generated from investing activities (b) | C58: -120214 | D58: -136881 | E58: -141570 | F58: -20028 | G58: -180868
B60: Cash flows from financing activities
B62: Net (Repayments) / Proceeds from borrowings | C62: 22730.262 | D62: 16379.727 | E62: -60116.972 | F62: -61420.981 | G62: 56669.694
B63: Net proceeds/ (repayments) from short-term borrowings | C63: 10852.092 | D63: -3788.2713 | E63: 52487.574 | F63: 4096.5075 | G63: -11879.409
B64: Payment of lease liabilities | C64: -22224.993 | D64: -20335.401 | E64: -16243.946 | F64: -17623.041 | G64: -19273.126
B66: Purchase of treasury shares and proceeds from exercise of share options | C66: -23.810707 | D66: -362.4443 | E66: -205.00964 | F66: 0 | G66: 2.4980018e-16
B70: Interest and other finance charges paid | C70: -60313.149 | D70: -41428.461 | E70: -11120.171 | F70: -18727.39 | G70: -12054.482
B71: Dividend paid (including tax) | C71: -1372.9327 | D71: -6283.9598 | E71: -3783.0825 | F71: -2998.2958 | G71: 0.2556634
B72: Proceeds from issuance of equity shares / perpetual bonds to NCI | C72: 0 | D72: 0 | E72: 0 | F72: 0 | G72: 36048.399
B73: Sale of interest in a subsidiary | C73: 145.77462 | D73: 13092.417 | E73: 27673.322 | F73: 0 | G73: 0
B74: Payment on Maturity forwards | C74: -440.21906 | D74: -817.60948 | E74: -569.78054 | F74: 1123.8936 | G74: -29.081506
B75: Purchase of shares from NCI | C75: -44.624267 | D75: -12525.392 | E75: -39.93991 | F75: -913 | G75: -9997.6469
B76: Net proceeds from issue of shares | C76: -28 | D76: 52254 | E76: 0 | F76: 0 | G76: 0
B77: Proceeds from issuance of Compulsorily convertible preference shares to NCI | C77: 6880 | D77: 0 | E77: 4000 | F77: 0 | G77: 7000
... B86: Cash and cash equivalents as at end of the period | C86: 73986.87 | D86: 91275.105 | E86: 74005.742 | F86: 97071.941 | G86: 90629.94

Sheet Trends file-4
A1: INDEX
A3: 4 | B3: Consolidated Summarised Statement of Operations as per Ind-AS (net of inter segment eliminations)
G4: ='Trends file-1'!$G$6 -> Amount in Rs Mn, except ratios
B5: Particulars | C5: Quarter Ended
C6: ='Trends file-1'!C8 -> 44651 | D6: ='Trends file-1'!D8 -> 44561 | E6: ='Trends file-1'!E8 -> 44469 | F6: ='Trends file-1'!F8 -> 44377 | G6: ='Trends file-1'!G8 -> 44286
B7: Total revenues | C7: 315003 | D7: 298666.37 | E7: 283263.5 | F7: 268536.23 | G7: 257473
B8: Total Revenues - Recasted for IUC | C8: 315003 | D8: 298666.37 | E8: 283263.5 | F8: 268536.23 | G8: 257473
B9: EBITDA | C9: 159984.32 | D9: 149047.21 | E9: 140177.11 | F9: 131894.36 | G9: 125831
B10: EBITDA / Total revenues | C10: 0.50788188 | D10: 0.49904251 | E10: 0.4948647 | F10: 0.4911604 | G10: 0.48871532
B11: EBIT | C11: 73149.268 | D11: 63446.885 | E11: 57563.989 | F11: 54370.636 | G11: 50480
B12: Finance cost (net) | C12: 38980.497 | D12: 43591.55 | E12: 40444.966 | F12: 40818.105 | G12: 38586
B13: Share of results of Joint Ventures / Associates | C13: 7136.2057 | D13: 6160.9404 | E13: 5988.2471 | F13: 4946.6314 | G13: 5274
B14: Profit before Tax | C14: 41305.576 | D14: 26016.875 | E14: 23068.424 | F14: 17454.316 | G14: 15807
B15: Income tax expense | C15: 14002.291 | D15: 9907.5035 | E15: 8491.2632 | F15: 8344.8932 | G15: 6495
B16: Profit after tax (before exceptional items) | C16: 27303.285 | D16: 16109.371 | E16: 14577.161 | F16: 9109.4224 | G16: 9312
B17: Non Controlling Interest | C17: 8700.5524 | D17: 8035.921 | E17: 8640.4019 | F17: 6445.0326 | G17: 6090
B18: Net income (before exceptional items) | C18: 18602.733 | D18: 8073.45 | E18: 5936.7588 | F18: 2664.3898 | G18: 3222
... B26: Cumulative Investments | C26: 4231487.4 | D26: 4179029.5 | E26: 4142438.6 | F26: 4061360 | G26: 3884792.4
B27: *Share of results of Joint Ventures/Associates includes the equity pick up of erstwhile Bharti Infratel Limited (now Indus Towers Limited) for periods represented.
B28: Region and Segment wise summarised statement of operations as per Ind-AS:
A30: 4.1 | B30: India South Asia- Summarised Statement of Operations as per Ind-AS (net of inter segment eliminations)
G31: ='Trends file-1'!$G$6 -> Amount in Rs Mn, except ratios
B32: Particulars | C32: Quarter Ended
C33: =$C$6 -> 44651 | D33: =$D$6 -> 44561 | E33: =$E$6 -> 44469 | F33: =$F$6 -> 44377 | G33: =$G$6 -> 44286
B34: Total revenues | C34: 225895.07 | D34: 210022.66 | E34: 199791.8 | F34: 189167.93 | G34: 184269
B35: Total Revenues - Recasted for IUC | C35: 225895.07 | D35: 210022.66 | E35: 199791.8 | F35: 189167.93 | G35: 184269
B36: Net revenue | C36: 186229.53 | D36: 173346.19 | E36: 164288.8 | F36: 155202.98 | G36: 151830
B37: EBITDA | C37: 114200.69 | D37: 103857.92 | E37: 98434.668 | F37: 92623.442 | G37: 89580
B38: EBITDA / Total revenues | C38: 0.50554754 | D38: 0.49450816 | E38: 0.49268622 | F38: 0.48963608 | G38: 0.48613711
B39: EBIT | C39: 41567.149 | D39: 32508.41 | E39: 29507.536 | F39: 28446.621 | G39: 27152
B40: Profit before Tax | C40: 14015.109 | D40: 6453.5024 | E40: 5135.3168 | F40: -3344.0756 | G40: -1263.4855
B41: Income tax expense | C41: 3856.8158 | D41: 975.5358 | E41: 416.01643 | F41: -791.93146 | G41: 109
B42: Profit after Tax (before exceptional items) | C42: 10158.293 | D42: 5477.9666 | E42: 4719.3004 | F42: -2552.1441 | G42: -1372.4855
B43: Non Controlling Interest | C43: 1644.4954 | D43: 1213.0254 | E43: 1245.073 | F43: 1340.0634 | G43: 984
B44: Net income (before exceptional items) | C44: 8513.798 | D44: 4264.9412 | E44: 3474.2274 | F44: -3892.2075 | G44: -2356.4855
B45: Capex | C45: 43155.147 | D45: 47049.753 | E45: 59407.352 | F45: 58113.085 | G45: 53007.259
... B47: Cumulative Investments | C47: 3538863.4 | D47: 3509004.8 | E47: 3472504.2 | F47: 3402127.8 | G47: 3230503.8
A50: 4.1.1 | B50: India - Summarised Statement of Operations as per Ind-AS (net of inter segment eliminations)
G51: ='Trends file-1'!$G$6 -> Amount in Rs Mn, except ratios
B52: Particulars | C52: Quarter Ended
C53: =$C$6 -> 44651 | D53: =$D$6 -> 44561 | E53: =$E$6 -> 44469 | F53: =$F$6 -> 44377 | G53: =$G$6 -> 44286
B54: Total revenues | C54: 225003.61 | D54: 209126.82 | E54: 198904.27 | F54: 188283.79 | G54: 183378
B55: Total Revenues - Recasted for IUC | C55: 225003.61 | D55: 209126.82 | E55: 198904.27 | F55: 188283.79 | G55: 183378
B56: Net revenue | C56: 185623.05 | D56: 172749.33 | E56: 163678.44 | F56: 154582.76 | G56: 151195.27
B57: EBITDA | C57: 114360.66 | D57: 104066.71 | E57: 98575.998 | F57: 92734.138 | G57: 89702.465
B58: EBITDA / Total revenues | C58: 0.50826143 | D58: 0.49762488 | E58: 0.49559519 | F58: 0.49252321 | G58: 0.48916699
B59: EBIT | C59: 42194.516 | D59: 33195.026 | E59: 30097.734 | F59: 28964.419 | G59: 27631.759
B60: Profit before Tax | C60: 15040.927 | D60: 7373.6455 | E60: 5665.2908 | F60: -2424.0299 | G60: -268.13012
B61: Income tax expense | C61: 3856.8158 | D61: 975.5358 | E61: 416.01643 | F61: -791.93146 | G61: 109.1039
B62: Profit after Tax (before exceptional items) | C62: 11184.111 | D62: 6398.1097 | E62: 5249.2743 | F62: -1632.0984 | G62: -377.23402
B63: Non Controlling Interest | C63: 1644.4954 | D63: 1213.0254 | E63: 1245.073 | F63: 1340.0634 | G63: 983.36369
B64: Net income (before exceptional items) | C64: 9539.6153 | D64: 5185.0844 | E64: 4004.2013 | F64: -2972.1618 | G64: -1360.5977
B65: Capex | C65: 42767.089 | D65: 46537.76 | E65: 57993.197 | F65: 57135.006 | G65: 51413.927
... B67: Cumulative Investments | C67: 3498207 | D67: 3461603.2 | E67: 3426398.8 | F67: 3357339.4 | G67: 3187006.3
B68: Note: Pursuant to reporting changes on account of deconsolidation of Bharti Infratel Limited, the definition of India geography has changed. Refer Glossary section of the qaurterly report for more details.
B69: B2C Services
A71: 4.1.1.1 | B71: Mobile Services India - Comprises of consolidated operations of Mobile Services India
G72: ='Trends file-1'!$G$6 -> Amount in Rs Mn, except ratios
B73: Particulars | C73: Quarter Ended
C74: =$C$6 -> 44651 | D74: =$D$6 -> 44561 | E74: =$E$6 -> 44469 | F74: =$F$6 -> 44377 | G74: =$G$6 -> 44286
B75: Total revenues | C75: 176167.89 | D75: 160917.04 | E75: 151913.7 | F75: 143055.61 | G75: 140797.53
B76: Total Revenues - Recasted for IUC | C76: 176167.89 | D76: 160917.04 | E76: 151913.7 | F76: 143055.61 | G76: 140797.53
B77: EBITDA | C77: 89215.332 | D77: 79434.084 | E77: 74679.231 | F77: 70335.22 | G77: 66896.954
B78: EBITDA / Total revenues | C78: 0.50642221 | D78: 0.49363377 | E78: 0.49158983 | F78: 0.49166348 | G78: 0.47512875
B79: EBIT | C79: 28740.57 | D79: 19000.387 | E79: 16111.12 | F79: 15700.455 | G79: 13506.573
B80: Capex | C80: 26177.632 | D80: 29734.289 | E80: 46293.046 | F80: 43744.247 | G80: 37392.686
B81: Operating Free Cash Flow | C81: 63037.7 | D81: 49699.795 | E81: 28386.185 | F81: 26590.973 | G81: 29504.268
B82: Cumulative Investments | C82: 2774592.3 | D82: 2774569.3 | E82: 2760475.2 | F82: 2707875.3 | G82: 2569539.7
A85: 4.1.1.2 | B85: Homes Services - Comprises of operations of Homes Services.
G86: ='Trends file-1'!$G$6 -> Amount in Rs Mn, except ratios
B87: Particulars | C87: Quarter Ended
C88: =$C$6 -> 44651 | D88: =$D$6 -> 44561 | E88: =$E$6 -> 44469 | F88: =$F$6 -> 44377 | G88: =$G$6 -> 44286
B89: Total revenues | C89: 8762.0578 | D89: 7968.7393 | E89: 7126.5198 | F89: 6532.6126 | G89: 6009.089
B90: EBITDA | C90: 4773.5691 | D90: 4357.5205 | E90: 3778.7742 | F90: 3229.5171 | G90: 3344.5647
B91: EBITDA / Total revenues | C91: 0.5448 | D91: 0.54682684 | E91: 0.53024118 | F91: 0.49436837 | G91: 0.55658432
B92: EBIT | C92: 1928.3942 | D92: 1640.1573 | E92: 1251.8706 | F92: 945.81017 | G92: 1239.6297
B93: Capex | C93: 4967.7889 | D93: 4062.0317 | E93: 3499.6503 | F93: 3891.9739 | G93: 3324.6922
B94: Operating Free Cash Flow | C94: -194.21982 | D94: 295.48884 | E94: 279.12395 | F94: -662.45684 | G94: 19.872495
B95: Cumulative Investments | C95: 113805.08 | D95: 111677.79 | E95: 108473.94 | F95: 104513.89 | G95: 100062.84
A97: 4.1.1.3 | B97: Digital TV Services - Comprises of operations of Digital TV Services.
G98: ='Trends file-1'!$G$6 -> Amount in Rs Mn, except ratios
B99: Particulars | C99: Quarter Ended
C100: =$C$6 -> 44651 | D100: =$D$6 -> 44561 | E100: =$E$6 -> 44469 | F100: =$F$6 -> 44377 | G100: =$G$6 -> 44286
B101: Total revenues | C101: 7551.7784 | D101: 7912.4454 | E101: 7979.0099 | F101: 8094.5149 | G101: 7673.1986
B102: EBITDA | C102: 4952.0217 | D102: 5318.8596 | E102: 5314.3857 | F102: 5420.7717 | G102: 5105.0719
B103: EBITDA / Total revenues | C103: 0.65574245 | D103: 0.67221438 | E103: 0.66604576 | F103: 0.66968456 | G103: 0.66531211
B104: EBIT | C104: 1370.9401 | D104: 2100.3019 | E104: 2204.4242 | F104: 2698.8098 | G104: 2483.736
B105: Capex | C105: 3143.297 | D105: 4373.7662 | E105: 2578.5871 | F105: 2931.5904 | G105: 3690.3759
B106: Operating Free Cash Flow | C106: 1808.7247 | D106: 945.09342 | E106: 2735.7986 | F106: 2489.1813 | G106: 1414.696
B107: Cumulative Investments | C107: 121493.2 | D107: 120844.37 | E107: 116710.37 | F107: 113798.37 | G107: 111003.7
B110: B2B Services
A112: 4.1.1.4 | B112: Airtel Business
G113: ='Trends file-1'!$G$6 -> Amount in Rs Mn, except ratios
B114: Particulars | C114: Quarter Ended
C115: =$C$6 -> 44651 | D115: =$D$6 -> 44561 | E115: =$E$6 -> 44469 | F115: =$F$6 -> 44377 | G115: =$G$6 -> 44286
B116: Total revenues | C116: 41798.32 | D116: 41058.526 | E116: 39953.065 | F116: 37893.218 | G116: 37019.96
B117: EBITDA | C117: 16450.991 | D117: 15823.696 | E117: 15922.426 | F117: 14684.871 | G117: 14867.042
B118: EBITDA / Total revenues | C118: 0.39358021 | D118: 0.38539367 | E118: 0.39852826 | F118: 0.38753296 | G118: 0.40159531
B119: EBIT | C119: 11682.383 | D119: 11288.446 | E119: 11500.06 | F119: 10471.737 | G119: 11027.939
B120: Capex | C120: 8478.3709 | D120: 8367.6732 | E120: 5621.9133 | F120: 6567.1948 | G120: 7006.1731
...

Sheet Trends file-5-SCH
A1: INDEX
A3: 5 | B3: Schedules to Financial Statements
A5: 5.1 | B5: India
A7: 5.1.1 | B7: Operating Expenses
G8: ='Trends file-4'!G4 -> Amount in Rs Mn, except ratios
B9: Particulars | C9: Quarter Ended
C10: ='Trends file-1'!C8 -> 44651 | D10: ='Trends file-1'!D8 -> 44561 | E10: ='Trends file-1'!E8 -> 44469 | F10: ='Trends file-1'!F8 -> 44377 | G10: ='Trends file-1'!G8 -> 44286
B11: Access charges | C11: 11657.386 | D11: 11495.266 | E11: 11129.188 | F11: 10609.737 | G11: 11209
B12: Licence fees, revenue share & spectrum charges | C12: 25567.952 | D12: 22876.571 | E12: 22376.662 | F12: 21345.738 | G12: 19578.735
B13: Network operations costs | C13: 49466.846 | D13: 49610.442 | E13: 46712.779 | F13: 43497.783 | G13: 45437.02
B14: Cost of good sold | C14: 2155.2138 | D14: 2005.6888 | E14: 1719.9582 | F14: 1745.5971 | G14: 1395
B15: Employee costs | C15: 5824.4715 | D15: 4980.3921 | E15: 5785.8416 | F15: 5379.0952 | G15: 5177.8055
B16: Selling, general and adminstration expense | C16: 17829.895 | D16: 14960.861 | E16: 13473.949 | F16: 13999.05 | G16: 12026.009
B17: Operating Expenses | C17: 112501.76 | D17: 105929.22 | E17: 101198.38 | F17: 96577.001 | G17: 94823.57
A19: 5.1.2 | B19: Depreciation and Amortisation
G20: =G8 -> Amount in Rs Mn, except ratios
B21: Particulars | C21: Quarter Ended
C22: ='Trends file-4'!$C$6 -> 44651 | D22: ='Trends file-4'!$D$6 -> 44561 | E22: ='Trends file-4'!$E$6 -> 44469 | F22: ='Trends file-4'!$F$6 -> 44377 | G22: ='Trends file-4'!$G$6 -> 44286
B23: Depreciation | C23: 54340 | D23: 53638.249 | E23: 51617.815 | F23: 47935.82 | G23: 46819.096
B24: Amortization | C24: 16919.017 | D24: 17129.841 | E24: 16744.719 | F24: 15457.042 | G24: 14948.176
B25: Depreciation and Amortisation | C25: 71259.016 | D25: 70768.09 | E25: 68362.534 | F25: 63392.862 | G25: 61767.272
A27: 5.1.3 | B27: Income Tax
G28: =G20 -> Amount in Rs Mn, except ratios
B29: Particulars | C29: Quarter Ended
C30: ='Trends file-4'!$C$6 -> 44651 | D30: ='Trends file-4'!$D$6 -> 44561 | E30: ='Trends file-4'!$E$6 -> 44469 | F30: ='Trends file-4'!$F$6 -> 44377 | G30: ='Trends file-4'!$G$6 -> 44286
B31: Current tax expense | C31: 1199.5001 | D31: 962.375 | E31: 1176.3455 | F31: 1164.1726 | G31: 843.87883
B32: Deferred tax expense / (income) | C32: 2657.3157 | D32: 13.1608 | E32: -760.32907 | F32: -1956.1041 | G32: -734.77493
B34: Income tax expense | C34: 3856.8158 | D34: 975.5358 | E34: 416.01643 | F34: -791.93146 | G34: 109.1039
A39: 5.2 | B39: South Asia
A41: 5.2.1 | B41: Operating Expenses
G42: =G28 -> Amount in Rs Mn, except ratios
B43: Particulars | C43: Quarter Ended
C44: ='Trends file-4'!$C$6 -> 44651 | D44: ='Trends file-4'!$D$6 -> 44561 | E44: ='Trends file-4'!$E$6 -> 44469 | F44: ='Trends file-4'!$F$6 -> 44377 | G44: ='Trends file-4'!$G$6 -> 44286
B45: Access charges | C45: 161.5317 | D45: 146.89126 | E45: 124.09184 | F45: 113.52466 | G45: 110.04947
B46: Licence fees, revenue share & spectrum charges | C46: 168.51904 | D46: 180.24156 | E46: 178.23511 | F46: 176.97672 | G46: 171.45834
B47: Network operations costs | C47: 480.38044 | D47: 452.78784 | E47: 429.66405 | F47: 456.94743 | G47: 372.79312
B48: Cost of good sold | C48: 0.20521351 | D48: 0.56629946 | E48: -1.4772172 | F48: 0.34377621 | G48: 0.2661113
B49: Employee costs | C49: 101.56029 | D49: 102.48518 | E49: 99.462312 | F49: 102.46365 | G49: 104.93749
B50: Selling, general and adminstration expense | C50: 247.79718 | D50: 301.6527 | E50: 269.21185 | F50: 212.01563 | G50: 344.45611
B51: Operating Expenses | C51: 1159.9939 | D51: 1184.6248 | E51: 1099.1879 | F51: 1062.2719 | G51: 1103.9606
A53: 5.2.2 | B53: Depreciation and Amortisation
G54: =G42 -> Amount in Rs Mn, except ratios
B55: Particulars | C55: Quarter Ended
C56: ='Trends file-4'!$C$6 -> 44651 | D56: ='Trends file-4'!$D$6 -> 44561 | E56: ='Trends file-4'!$E$6 -> 44469 | F56: ='Trends file-4'!$F$6 -> 44377 | G56: ='Trends file-4'!$G$6 -> 44286
B57: Depreciation | C57: 429.62261 | D57: 437.07699 | E57: 408.13227 | F57: 370.54001 | G57: 329.10918
B58: Amortization | C58: 37.779828 | D58: 40.749388 | E58: 40.736145 | F58: 36.562724 | G58: 28.082584
B59: Depreciation and Amortisation | C59: 467.40244 | D59: 477.82638 | E59: 448.86842 | F59: 407.10273 | G59: 357.19176
A61: 5.3 | B61: Africa
A63: 5.3.1 | B63: Operating Expenses (In Constant Currency)
G64: Amount in US$ Mn
B65: Particulars | C65: Quarter Ended
C66: ='Trends file-4'!$C$6 -> 44651 | D66: ='Trends file-4'!$D$6 -> 44561 | E66: ='Trends file-4'!$E$6 -> 44469 | F66: ='Trends file-4'!$F$6 -> 44377 | G66: ='Trends file-4'!$G$6 -> 44286
B67: Access charges | C67: 105.46579 | D67: 103.44502 | E67: 99.532363 | F67: 101.40012 | G67: 95.785476
B68: Licence fees, revenue share & spectrum charges | C68: 58.712986 | D68: 56.959248 | E68: 56.388166 | F68: 52.375598 | G68: 52.611729
B69: Network operations costs | C69: 212.07615 | D69: 203.70075 | E69: 202.44509 | F69: 195.11175 | G69: 176.99537
B70: Cost of good sold | C70: 60.521163 | D70: 61.488654 | E70: 57.383222 | F70: 54.431489 | G70: 47.115598
B71: Employee costs | C71: 80.874244 | D71: 80.507437 | E71: 74.616625 | F71: 71.095248 | G71: 68.659205
B72: Selling, general and adminstration expense | C72: 100.15241 | D72: 107.41306 | E72: 103.69457 | F72: 103.48258 | G72: 98.10037
B73: Operating Expenses | C73: 617.80274 | D73: 613.51417 | E73: 594.06004 | F73: 577.89679 | G73: 539.26775
B87: Note: Above nos have been re-instated to 31st Mar'21 closing constant currency except Capex, OFCF & Cumulative Investments. Accordingly previous quarter nos. have been re-instated for like to like comparisons.
A89: 5.3.2 | B89: Depreciation and Amortisation (In Constant Currency)
G90: =G64 -> Amount in US$ Mn
B91: Particulars | C91: Quarter Ended
C92: ='Trends file-4'!$C$6 -> 44651 | D92: ='Trends file-4'!$D$6 -> 44561 | E92: ='Trends file-4'!$E$6 -> 44469 | F92: ='Trends file-4'!$F$6 -> 44377 | G92: ='Trends file-4'!$G$6 -> 44286
B93: Depreciation | C93: 159.24361 | D93: 161.98522 | E93: 154.27029 | F93: 152.33862 | G93: 145.94867
B94: Amortization | C94: 29.593734 | D94: 28.486153 | E94: 28.932351 | F94: 27.92568 | G94: 28.238838
B95: Depreciation and Amortisation | C95: 188.83734 | D95: 190.47137 | E95: 183.20264 | F95: 180.2643 | G95: 174.18751
B105: Note: Above nos have been re-instated to 31st Mar'21 closing constant currency except Capex, OFCF & Cumulative Investments. Accordingly previous quarter nos. have been re-instated for like to like comparisons.
A107: 5.3.3 | B107: Income Tax
G108: =G90 -> Amount in US$ Mn
B109: Particulars | C109: Quarter Ended
C110: ='Trends file-4'!$C$6 -> 44651 | D110: ='Trends file-4'!$D$6 -> 44561 | E110: ='Trends file-4'!$E$6 -> 44469 | F110: ='Trends file-4'!$F$6 -> 44377 | G110: ='Trends file-4'!$G$6 -> 44286
B111: Current tax expense | C111: 85.802733 | D111: 92.700519 | E111: 83.150341 | F111: 83.0954 | G111: 76.606393
B113: Deferred tax expense / (income) | C113: 35.477427 | D113: 24.291568 | E113: 31.742064 | F113: 33.708711 | G113: 5.9279351
B114: Income tax expense | C114: 121.28016 | D114: 117.49209 | E114: 115.09241 | F114: 116.80411 | G114: 82.534328
B125: Note: Above table reflects the USD reported numbers.
A127: 5.4 | B127: Schedule of Consolidated Net Debt
B129: In INR | G129: ='Trends file-4'!G4 -> Amount in Rs Mn, except ratios
B130: Particulars | C130: Quarter Ended
C131: ='Trends file-4'!$C$6 -> 44651 | D131: ='Trends file-4'!$D$6 -> 44561 | E131: ='Trends file-4'!$E$6 -> 44469 | F131: ='Trends file-4'!$F$6 -> 44377 | G131: ='Trends file-4'!$G$6 -> 44286
B132: Long term debt, net of current portion | C132: 424648.43 | D132: 416054.18 | E132: 404112.98 | F132: 450940.85 | G132: 421603.39
B133: Short-term borrowings and current portion of long-term debt | C133: 193794.66 | D133: 155841.99 | E133: 155988.81 | F133: 116313.93 | G133: 192302.98
B134: Deferred payment liability | C134: 709205.01 | D134: 758628.82 | E134: 892938.82 | F134: 788049.92 | G134: 681930.8
C135: 0 | D135: 0 | E135: 0 | F135: 0 | G135: 0
B136: Less:
B137: Cash and Cash Equivalents | C137: 60959.859 | D137: 73015.207 | E137: 61707.55 | F137: 84917.419 | G137: 80860.459
B140: Investments & Receivables | C140: 31249.409 | D140: 18435.895 | E140: 77920.713 | F140: 5270.099 | G140: 59852.862
B142: Net Debt excluding Lease Obligations | C142: 1235438.8 | D142: 1239073.9 | E142: 1313412.4 | F142: 1265117.2 | G142: 1155123.8
B143: Lease Obligation | C143: 367634.04 | D143: 352346.29 | E143: 348981.31 | F143: 331104.05 | G143: 329952.62
B144: Net Debt including Lease Obligations | C144: 1603072.9 | D144: 1591420.2 | E144: 1662393.7 | F144: 1596221.2 | G144: 1485076.5
B148: In USD | G148: =G108 -> Amount in US$ Mn
B149: Particulars | C149: Quarter Ended
C150: ='Trends file-4'!$C$6 -> 44651 | D150: ='Trends file-4'!$D$6 -> 44561 | E150: ='Trends file-4'!$E$6 -> 44469 | F150: ='Trends file-4'!$F$6 -> 44377 | G150: ='Trends file-4'!$G$6 -> 44286
B151: Long term debt, net of current portion | C151: 5593.7355 | D151: 5590.9989 | E151: 5449.7553 | F151: 6075.323 | G151: 5745.0895
B152: Short-term borrowings and current portion of long-term debt | C152: 2552.7848 | D152: 2094.2282 | E152: 2103.6218 | F152: 1567.0452 | G152: 2620.4671
B153: Deferred payment liability | C153: 9342.0933 | D153: 10194.569 | E153: 12041.925 | F153: 10617.042 | G153: 9292.5093
B155: Less:
B156: Cash and Cash Equivalents | C156: 803.0015 | D156: 981.18937 | E156: 832.17086 | F156: 1144.0541 | G156: 1101.8663
B159: Investments & Receivables | C159: 411.63682 | D159: 247.74434 | E159: 1050.8171 | F159: 71.001671 | G159: 815.60077
B161: Net Debt excluding Finance Lease Obligations | C161: 16273.975 | D161: 16650.862 | E161: 17712.314 | F161: 17044.354 | G161: 15740.599
...

Sheet Trends file-6-Ops
A1: INDEX | F1: =1000 -> 1000
A3: 6.1 Operational Performance - INDIA
A5: Parameters | B5: Unit | C5: ='Trends file-5-SCH'!C10 -> 44651 | D5: ='Trends file-5-SCH'!D10 -> 44561 | E5: ='Trends file-5-SCH'!E10 -> 44469 | F5: ='Trends file-5-SCH'!F10 -> 44377 | G5: ='Trends file-5-SCH'!G10 -> 44286
A7: Total Customers Base | B7: 000's | C7: 359903.57 | D7: 355872.91 | E7: 354510.56 | F7: 350866.94 | G7: 350304.39
A9: Mobile Services
A10: Customer Base | B10: 000's | C10: 326043.25 | D10: 322917.59 | E10: 323476.47 | F10: 321238.12 | G10: 321373.51
A12: Net Additions | B12: 000's | C12: 3125.661 | D12: -558.875 | E12: 2238.345 | F12: -135.387 | G12: 13425.924
A13: Pre-Paid (as % of total Customer Base) | B13: % | C13: 0.94539226 | D13: 0.94551319 | E13: 0.94659875 | F13: 0.94732225 | G13: 0.9482444
A14: Monthly Churn | B14: % | C14: 0.028139047 | D14: 0.029222073 | E14: 0.030038177 | F14: 0.027981353 | G14: 0.022472763
A16: Average Revenue Per User (ARPU) | B16: Rs | C16: 178.25448 | D16: 162.60633 | E16: 153.43463 | F16: 146.13668 | G16: 145.21147
A17: Average Revenue Per User (ARPU) | B17: US | C17: 2.3714039 | D17: 2.1773866 | E17: 2.0719127 | F17: 1.9905788 | G17: 1.9822062
A18: Average Revenue Per User (ARPU) - Recasted for IUC | B18: Rs | C18: 178.25448 | D18: 162.51054 | E18: 153.43463 | F18: 146.13668 | G18: 145.21147
A19: Revenue per site per month | B19: Rs | C19: 246442.29 | D19: 232009.6 | E19: 224223.77 | F19: 214416.25 | G19: 215408.56
A20: Revenue per site per month - Recasted for IUC | B20: Rs | C20: 246442.29 | D20: 232009.6 | E20: 224223.77 | F20: 214416.25 | G20: 215408.56
A26: Voice
A27: Minutes on the network | B27: Mn | C27: 1051115.7 | D27: 1029802.1 | E27: 1020414.6 | F27: 1002263.3 | G27: 996793.1
A29: Voice Usage per customer | B29: min | C29: 1082.7037 | D29: 1060.6729 | E29: 1052.8949 | F29: 1043.988 | G29: 1052.798
A40: Data
A41: Data Customer Base | B41: 000's | C41: 208448.43 | D41: 202950.64 | E41: 200027.1 | F41: 192934.93 | G41: 188635.41
A42: Of which 4G data customers | B42: 000's | C42: 200786.28 | D42: 195540.68 | E42: 192538.56 | F42: 184426.83 | G42: 179292.94
A43: As % of customer base | B43: % | C43: 0.63932753 | D43: 0.6284905 | E43: 0.61836678 | F43: 0.60059787 | G43: 0.58696626
A44: Total MBs on the network | B44: Mn MBs | C44: 11849334 | D44: 11311780 | E44: 11270769 | F44: 10771051 | G44: 9207030.3
A46: Data Usage per customer | B46: MBs | C46: 19228.494 | D46: 18726.723 | E46: 19065.72 | F46: 18931.596 | G46: 16839.763
A49: Homes Services
A50: Homes Customers | B50: 000's | C50: 4482.8513 | D50: 4160.1123 | E50: 3819.0793 | F50: 3351.7103 | G50: 3066.5153
A53: Net Additions | B53: 000's | C53: 322.739 | D53: 341.033 | E53: 467.369 | F53: 285.195 | G53: 273.52
A54: Average Revenue Per User (ARPU) | B54: Rs | C54: 650.21634 | D54: 656.98566 | E54: 661.12382 | F54: 681.35662 | G54: 684.06609
A55: Average Revenue Per User (ARPU) | B55: US | C55: 8.6501364 | D55: 8.7973932 | E55: 8.9275206 | F55: 9.2809965 | G55: 9.3378301
A58: Digital TV Services
A59: Digital TV Customers | B59: 000's | C59: 17558.239 | D59: 18066.137 | E59: 17987.347 | F59: 17998.514 | G59: 17716.127
A60: Net additions | B60: 000's | C60: -507.898 | D60: 78.79 | E60: -11.166777 | F60: 282.387 | G60: -156.13981
A61: Average Revenue Per User (ARPU) * | B61: Rs | C61: 141.73459 | D61: 145.98992 | E61: 147.79085 | F61: 150.73214 | G61: 143.83368
A62: Average Revenue Per User (ARPU) | B62: US | C62: 1.8855625 | D62: 1.9548839 | E62: 1.9957016 | F62: 2.0531751 | G62: 1.9633987
A63: Monthly Churn | B63: % | C63: 0.021251353 | D63: 0.020534765 | E63: 0.02165758 | F63: 0.013584787 | G63: 0.02158276
A82: Parameters | B82: Unit | C82: =C5 -> 44651 | D82: =D5 -> 44561 | E82: =E5 -> 44469 | F82: =F5 -> 44377 | G82: =G5 -> 44286
A83: Mobile Services
A84: Census Towns | B84: Nos | C84: 7913 | D84: 7913 | E84: 7913 | F84: 7913 | G84: 7907
A85: Non-Census Towns & Villages | B85: Nos | C85: 795126 | D85: 794484 | E85: 793591 | F85: 793350 | G85: 792827
A86: Population Coverage | B86: % | C86: 0.95655404 | D86: 0.9563317 | E86: 0.95562185 | F86: 0.95526101 | G86: 0.95476298
A87: Optic Fibre Network | B87: R kms | C87: 355079 | D87: 346243 | E87: 340690 | F87: 332542 | G87: 324825
A88: Network towers | B88: Nos | C88: 237577 | D88: 230562 | E88: 222812 | F88: 219310 | G88: 216901
A89: Of which Mobile Broadband towers | B89: Nos | C89: 236882 | D89: 229823 | E89: 221979 | F89: 218328 | G89: 215801
A90: Total Mobile Broadband Base stations | B90: Nos | C90: 752136 | D90: 748335 | E90: 717534 | F90: 661750 | G90: 606783
C91: 0 | D91: 0 | E91: 0 | F91: 0 | G91: 0
A92: Homes Services - Cities covered | B92: Nos | C92: 847 | D92: 672 | E92: 523 | F92: 387 | G92: 291
C93: 0 | D93: 0 | E93: 0 | F93: 0 | G93: 0
A94: Airtel Business - Submarine Cable System | B94: Nos | C94: 7 | D94: 7 | E94: 7 | F94: 7 | G94: 7
A96: Digital TV Services
A97: Districts Covered | B97: Nos | C97: 639 | D97: 639 | E97: 639 | F97: 639 | G97: 639
A98: Coverage | B98: % | C98: 0.9984375 | D98: 0.9984375 | E98: 0.9984375 | F98: 0.9984375 | G98: 0.9984375
A100: Bharti Infratel Standalone
A101: Parameters | B101: Unit | C101: =C82 -> 44651 | D101: =D82 -> 44561 | E101: =E82 -> 44469 | F101: =F82 -> 44377 | G101: =G82 -> 44286
A102: Total Towers | B102: No.
A103: Total Co-locations | B103: No.
A104: Key Indicators
A105: Sharing Revenue per sharing operator per month | B105: Rs.
A106: Average Sharing Factor | B106: Times
A108: Indus Towers
A109: Parameters | B109: Unit | C109: =C101 -> 44651 | D109: =D101 -> 44561 | E109: =E101 -> 44469 | F109: =F101 -> 44377 | G109: =G101 -> 44286
A110: Total Towers | B110: No.
A111: Total Co-locations | B111: No.
A112: Average Sharing Factor | B112: Times
A114: Bharti Infratel Consolidated
A115: Parameters | B115: Unit | C115: =C109 -> 44651 | D115: =D109 -> 44561 | E115: =E109 -> 44469 | F115: =F109 -> 44377 | G115: =G109 -> 44286
A116: Total Towers | B116: No.
A117: Total Co-locations | B117: No.
A118: Average Sharing Factor | B118: Times
A122: 6.2 Operational Performance - AFRICA
A124: Parameters | B124: Unit | C124: =C115 -> 44651 | D124: =D115 -> 44561 | E124: =E115 -> 44469 | F124: =F115 -> 44377 | G124: =G115 -> 44286
A125: Customer Base | B125: 000's | C125: 128428.18 | D125: 125762.06 | E125: 122697.15 | F125: 120795.91 | G125: 118192.27
B126: %
A127: Net Additions | B127: 000's | C127: 2666.122 | D127: 3064.913 | E127: 1901.243 | F127: 2603.638 | G127: -710.958
A129: Monthly Churn | B129: % | C129: 0.043049191 | D129: 0.04205842 | E129: 0.043369338 | F129: 0.036211815 | G129: 0.038776977
A130: Average Revenue Per User (ARPU) | B130: US | C130: 3.2102999 | D130: 3.258437 | E130: 3.136207 | F130: 3.0899953 | G130: 2.9000669
C131: 0 | D131: 0 | E131: 0 | F131: 0 | G131: 0
A133: Voice
A134: Voice Revenue | B134: $ Mn | C134: 614.53521 | D134: 604.41667 | E134: 573.52895 | F134: 558.5745 | G134: 540.87325
A135: Minutes on the network | B135: Mn | C135: 98407.947 | D135: 97411.96 | E135: 93821.462 | F135: 89025.943 | G135: 84963.6
A136: Voice Average Revenue Per User (ARPU) | B136: US$ | C136: 1.6137777 | D136: 1.6284982 | E136: 1.5678591 | F136: 1.5600218 | G136: 1.5275698
A137: Voice Usage per customer | B137: min | C137: 258.42059 | D137: 262.46001 | E137: 256.48023 | F137: 248.63722 | G137: 239.95979
A147: Data
A148: Data Revenue | B148: $ Mn | C148: 398.09084 | D148: 392.94635 | E148: 373.09319 | F148: 354.7027 | G148: 311.36973
A149: Data Customer Base | B149: 000's | C149: 46733.957 | D149: 45113.751 | E149: 43920.006 | F149: 42433.68 | G149: 40583.674
A150: As % of Customer Base | B150: % | C150: 0.36389175 | D150: 0.35872305 | E150: 0.35795457 | F150: 0.35128409 | G150: 0.34336995
A151: Total MBs on the network | B151: Mn MBs | C151: 509303.47 | D151: 478813.01 | E151: 448911.88 | F151: 410723.47 | G151: 348230.38
A152: Data Average Revenue Per User (ARPU) | B152: US$ | C152: 2.9034641 | D152: 2.9428436 | E152: 2.8714106 | F152: 2.8519585 | G152: 2.589121
A153: Data Usage per customer | B153: MBs | C153: 3714.5902 | D153: 3585.914 | E153: 3454.9286 | F153: 3302.3889 | G153: 2895.627
A155: Airtel Money
A156: Transaction Value | B156: US$ Mn | C156: 16076.818 | D156: 16277.823 | E156: 15197.944 | F156: 14563.949 | G156: 12439.71
A157: Transaction Value per Subs | B157: US$ | C157: 209.50322 | D157: 219.01427 | E157: 215.44679 | F157: 215.87481 | G157: 192.24428
A158: Airtel Money Revenue | B158: $ Mn | C158: 140.59216 | D158: 140.21481 | E158: 129.46983 | F158: 123.0703 | G158: 109.02713
A159: Active Customers | B159: 000's | C159: 26154.627 | D159: 25666.984 | E159: 23942.402 | F159: 23082.859 | G159: 21670.111
A160: Airtel Money ARPU | B160: US$ | C160: 1.8321106 | D160: 1.8865572 | E160: 1.8353707 | F160: 1.8242152 | G160: 1.6849141
A161: Network & coverage
A162: Network towers | B162: Nos | C162: 28797 | D162: 27422 | E162: 26751 | F162: 26104 | G162: 25368
A163: Owned towers | B163: Nos | C163: 2048 | D163: 4097 | E163: 4562 | F163: 4505 | G163: 4627
A164: Leased towers | B164: Nos | C164: 26749 | D164: 23325 | E164: 22189 | F164: 21599 | G164: 20741
A165: Of which Mobile Broadband towers | B165: Nos | C165: 27782 | D165: 26278 | E165: 25600 | F165: 24701 | G165: 23826
A166: Total Mobile Broadband Base stations | B166: Nos | C166: 92304 | D166: 88572 | E166: 85205 | F166: 81319 | G166: 76563
A167: Revenue Per site Per Month | B167: US$ | C167: 14456.201 | D167: 14830.625 | E167: 14443.869 | F167: 14303.322 | G167: 13684.258
...
